Workbook

Sheet Family Edition
A1: FAMILY EDITION — build it for 2-10 people (the active plan)
A2: Private family tool. Almost everything is free-tier or pennies. No team, no legal, no deposits.
A4: Item | B4: Monthly $ | C4: Note
A5: Hosting (Vercel free tier) | B5: 0 | C5: Free for a small private app
A6: Database (Neon / Supabase free) | B6: 0 | C6: Serverless Postgres free tier
A7: Auth (Clerk free tier) | B7: 0 | C7: Free well beyond 10 users
A8: AI (Claude API, family usage) | B8: 3 | C8: Pennies per search; ~$1-5/mo realistic
A9: Flight data (Duffel sandbox / pay-per-use) | B9: 0 | C9: Free to test; pay only if you book
A10: Monitoring (Sentry free) | B10: 0 | C10: Free tier
A11: Domain (optional, ~$12/yr) | B11: 1 | C11: Optional
A12: TOTAL monthly (Family Edition) | B12: =SUM(B5:B11) -> 4 | C12: vs. $70k-380k to HIRE A TEAM for the public platform
A14: To build: your own time (evenings/weekends) | B14: 0 | C14: $0 in wages — you build it
A15: One-off legal / deposits | B15: 0 | C15: None — private family use is not a public service
A17: The other sheets = SCALE EDITION (only if you grow it public later).

Sheet Assumptions
A1: FlightAI — Cost Model & Unit Economics
A2: All blue cells are inputs you can change. Yellow = key levers. Figures are 2026 planning estimates (USD) — verify live.
A4: ASSUMPTIONS (edit the blue values)
A5: Item | B5: Value | C5: Note / source
A6: Revenue — affiliate commission per booked trip | B6: 10 | C6: Provisional; verify with provider (Duffel/Kiwi/aggregator)
A7: Booking conversion rate (search → booking) | B7: 0.02 | C7: UNPROVEN — key sensitivity. Stored as fraction.
A8: Searches per active user per month | B8: 8 | C8: Assumption; tune from real usage
A9: Provider search calls per search — NAIVE fan-out | B9: 40 | C9: Date grid x airports x providers
A10: Provider search calls per search — OPTIMIZED | B10: 6 | C10: Native flexible endpoints + cache (ADR-0007)
A11: Provider cost per search call | B11: 0.005 | C11: Duffel excess-search fee past 1,500:1 ratio
A12: LLM cost per search | B12: 0.02 | C12: 1 intake (Haiku) + 1 explanation (Sonnet), cached
A13: Infra cost per search | B13: 0.005 | C13: Compute + snapshot storage (ADR-0009)
A14: Duffel cost per confirmed order | B14: 3 | C14: If booking via Duffel (not pure affiliate)
A15: Duffel managed-content % of order value | B15: 0.01 | C15: +1% of order; stored as fraction
A16: Average order value | B16: 300 | C16: Illustrative round-trip fare
A17: Phase B — monthly active users (beta) | B17: 5000 | C17: Scenario
A18: Phase C — monthly active users (growth) | B18: 100000 | C18: Scenario

Sheet Unit Economics
A1: Unit Economics — per search & per booking
A2: Green = pulled from Assumptions. Black = computed. This is the make-or-break math (business model §2a).
A4: PER SEARCH
A5: Metric | B5: Value | C5: Formula / note
A6: Revenue per search | B6: =Assumptions!$B$6*Assumptions!$B$7 -> 0.2 | C6: commission x conversion rate
A7: Provider search cost — OPTIMIZED | B7: =Assumptions!$B$10*Assumptions!$B$11 -> 0.03 | C7: optimized calls x cost/call
A8: Provider search cost — NAIVE | B8: =Assumptions!$B$9*Assumptions!$B$11 -> 0.2 | C8: naive calls x cost/call (the danger)
A9: LLM cost per search | B9: =Assumptions!$B$12 -> 0.02
A10: Infra cost per search | B10: =Assumptions!$B$13 -> 0.005
A11: Total cost per search — OPTIMIZED | B11: =B7+B9+B10 -> 0.055
A12: Total cost per search — NAIVE | B12: =B8+B9+B10 -> 0.225
A13: Gross margin per search — OPTIMIZED | B13: =B6-B11 -> 0.145
A14: Gross margin per search — NAIVE | B14: =B6-B12 -> -0.025
A15: Break-even provider calls per search | B15: =IFERROR((B6-B9-B10)/Assumptions!$B$11,0) -> 35 | C15: Max provider calls before margin goes negative
A17: PER BOOKING
A18: Metric | B18: Value | C18: Note
A19: Affiliate model — our booking cost | B19: 0 | C19: Affiliate handoff = no ticketing cost/PCI (ADR-0003)
A20: If booking via Duffel — cost per order | B20: =Assumptions!$B$14+Assumptions!$B$15*Assumptions!$B$16 -> 6 | C20: $3 + 1% x AOV + ancillaries

Sheet Monthly Costs
A1: Monthly Software / Service Costs by Phase
A2: Representative monthly USD. Usage-based rows are formula-driven from Assumptions/Unit Economics. Fixed rows are blue estimates.
A4: Category | B4: Phase A: MVP build | C4: Phase B: Beta | D4: Phase C: Growth | E4: Note
A5: — Monthly searches (derived) | B5: 0 | C5: =Assumptions!$B$17*Assumptions!$B$8 -> 40000 | D5: =Assumptions!$B$18*Assumptions!$B$8 -> 800000 | E5: MAU x searches/user
A6: Cloud compute + data (AWS) | B6: 200 | C6: 900 | D6: 8000 | E6: Credit-offset in A/B (AWS Activate)
A7: Auth (Clerk -> Ory) | B7: 0 | C7: 0 | D7: 1025 | E7: Free <50k MRU; Clerk ~$1,025 at 100k, or self-host Ory
A8: Monitoring + logging (Grafana + Sentry) | B8: 0 | C8: 75 | D8: 2000 | E8: Free tier early; scales with series/GB
A9: Frontend host (Vercel) | B9: 10 | C9: 80 | D9: 500 | E9: Or self-host on AWS at scale
A10: CI/CD (GitHub Actions) | B10: 6 | C10: 50 | D10: 500 | E10: Free minutes early; self-host runners for heavy jobs
A11: Email / collaboration | B11: 20 | C11: 90 | D11: 300 | E11: Google Workspace per seat
A12: Flight-API search cost (usage) | B12: 0 | C12: =C5*'Unit Economics'!$B$7 -> 1200 | D12: =D5*'Unit Economics'!$B$7 -> 24000 | E12: searches x optimized provider cost/search
A13: LLM cost (usage) | B13: 150 | C13: =C5*'Unit Economics'!$B$9 -> 800 | D13: =D5*'Unit Economics'!$B$9 -> 16000 | E13: Phase A = dev/testing estimate; B/C = searches x LLM/search
A14: TOTAL software/service (excl. salaries) | B14: =SUM(B6:B11)+B12+B13 -> 386 | C14: =SUM(C6:C11)+C12+C13 -> 3195 | D14: =SUM(D6:D11)+D12+D13 -> 52325 | E14: Excludes salaries (the dominant cost) and one-off at-start costs
A16: Bookings / month (derived) | B16: 0 | C16: =C5*Assumptions!$B$7 -> 800 | D16: =D5*Assumptions!$B$7 -> 16000 | E16: For revenue side; searches x conversion

Sheet At-Start One-off
A1: At-Start & One-off Costs (pre-launch)
A2: The cash costs that actually exist at the beginning. Blue = editable estimate.
A4: Item | B4: Low | C4: High | D4: Note
A5: Legal — provider ToS, GDPR DPIA, seller-of-travel | B5: 2000 | C5: 15000 | D5: Gated by due-diligence spike; needed before launch
A6: Business setup — incorporation, accounting | B6: 500 | C6: 3000 | D6: Jurisdiction-dependent
A7: Flight-provider deposit / minimums (if GDS Enterprise) | B7: 0 | C7: 20000 | D7: BIG UNKNOWN — pin down in spike (R1/R22)
A8: Domain (annual) | B8: 12 | C8: 40 | D8: One-off-ish
A9: Wizard-of-Oz validation (optional) | B9: 200 | C9: 2000 | D9: Real bookings + time; de-risks the business
A10: Design / branding (optional) | B10: 0 | C10: 5000 | D10: Can defer
A11: TOTAL one-off (excl. salaries) | B11: =SUM(B5:B10) -> 2712 | C11: =SUM(C5:C10) -> 45040
A13: Recurring software at start (from Monthly Costs, Phase A) | B13: ='Monthly Costs'!$B$14 -> 386 | D13: Per month; largely free-tier / credit-offset
A15: NOTE: People (salaries) are the dominant cost and are excluded here.

Sheet Startup Credits
A1: Startup Credits — make the beginning nearly free
A3: Program | B3: Value | C3: Note
A4: AWS Activate Founders | B4: $1,000 | C4: Self-serve, any founder
A5: AWS Activate Builders | B5: $1,000–$5,000 | C5: Direct application
A6: AWS Activate Portfolio | B6: $25,000–$100,000 | C6: Via accelerator/VC
A7: AWS Activate GenAI | B7: up to $300,000 | C7: Bedrock/SageMaker — covers Claude-on-Bedrock
A8: Anthropic / OpenAI startup programs | B8: varies | C8: Apply for LLM credits
A9: Sentry / Stripe / others | B9: free/discounted tiers | C9: Stack them
